com/__init__.py
com/wuage/__init__.py
com/wuage/search/__init__.py
com/wuage/search/api/__init__.py
com/wuage/search/api/simTerms.py
com/wuage/search/utils/__init__.py
com/wuage/search/utils/reportChannel.py
com/wuage/search/utils/termSimilarity.py
searchHttpAPI-1.0.0.dev1.dist-info/METADATA
searchHttpAPI-1.0.0.dev1.dist-info/RECORD
searchHttpAPI-1.0.0.dev1.dist-info/WHEEL
searchHttpAPI-1.0.0.dev1.dist-info/top_level.txt
