Metadata-Version: 2.1
Name: searchHttpAPI
Version: 1.0.0.dev1
Summary: A http client Testing python project
Home-page: https://gitlab.wuage-inc.com/jianxing.wei/monitor_search_suggestionAPI.git
Author: Jianxing.wei
Author-email: jianxing.wei@wuage.com
License: MIT
Keywords: REST API test python
Platform: UNKNOWN
Classifier: Development Status :: 4 - Beta
Classifier: Intended Audience :: Developers
Classifier: Topic :: Software Development :: Build Tools
Classifier: License :: OSI Approved :: MIT License
Classifier: Programming Language :: Python :: 3.5
Classifier: Programming Language :: Python :: 3.6
